{
  "mode": "pre",
  "tag": "next",
  "initialVersions": {
    "@neo4j/graph-schema-utils": "0.0.1",
    "@neo4j/graph-json-schema": "0.0.1"
  },
  "changesets": [
    "big-birds-arrive",
    "brave-rivers-dream",
    "bright-eels-sniff",
    "cool-chefs-listen",
    "eight-suns-doubt",
    "friendly-masks-punch",
    "gentle-mice-battle",
    "great-falcons-move",
    "perfect-moons-leave",
    "polite-ears-help",
    "rich-cameras-drive",
    "rude-camels-speak",
    "short-radios-cheer",
    "slow-wombats-try",
    "yellow-avocados-flash"
  ]
}
